dotnet_nlp/rule_engine/__init__.py
dotnet_nlp/rule_engine/runtimeconfig.json
dotnet_nlp/rule_engine/bundle/__init__.py
dotnet_nlp/rule_engine/bundle/converter.py
dotnet_nlp/rule_engine/bundle/initializer.py
dotnet_nlp/rule_engine/bundle/wrappers.py
dotnet_nlp/rule_engine/dlls/DotnetNlp.RuleEngine.Bundle.deps.json
dotnet_nlp/rule_engine/dlls/DotnetNlp.RuleEngine.Bundle.dll
dotnet_nlp/rule_engine/dlls/DotnetNlp.RuleEngine.Bundle.pdb
dotnet_nlp/rule_engine/dlls/DotnetNlp.RuleEngine.Core.dll
dotnet_nlp/rule_engine/dlls/DotnetNlp.RuleEngine.Core.pdb
dotnet_nlp/rule_engine/dlls/DotnetNlp.RuleEngine.Mechanics.Peg.dll
dotnet_nlp/rule_engine/dlls/DotnetNlp.RuleEngine.Mechanics.Peg.pdb
dotnet_nlp/rule_engine/dlls/DotnetNlp.RuleEngine.Mechanics.Regex.dll
dotnet_nlp/rule_engine/dlls/DotnetNlp.RuleEngine.Mechanics.Regex.pdb
dotnet_nlp/rule_engine/dlls/IronMeta.Library.dll
dotnet_nlp/rule_engine/dlls/Microsoft.CSharp.dll
dotnet_nlp/rule_engine/dlls/Microsoft.CodeAnalysis.CSharp.dll
dotnet_nlp/rule_engine/dlls/Microsoft.CodeAnalysis.dll
dotnet_nlp/rule_engine/dlls/Microsoft.VisualBasic.Core.dll
dotnet_nlp/rule_engine/dlls/Microsoft.VisualBasic.dll
dotnet_nlp/rule_engine/dlls/Microsoft.Win32.Primitives.dll
dotnet_nlp/rule_engine/dlls/Microsoft.Win32.Registry.dll
dotnet_nlp/rule_engine/dlls/System.AppContext.dll
dotnet_nlp/rule_engine/dlls/System.Buffers.dll
dotnet_nlp/rule_engine/dlls/System.Collections.Concurrent.dll
dotnet_nlp/rule_engine/dlls/System.Collections.Immutable.dll
dotnet_nlp/rule_engine/dlls/System.Collections.NonGeneric.dll
dotnet_nlp/rule_engine/dlls/System.Collections.Specialized.dll
dotnet_nlp/rule_engine/dlls/System.Collections.dll
dotnet_nlp/rule_engine/dlls/System.ComponentModel.Annotations.dll
dotnet_nlp/rule_engine/dlls/System.ComponentModel.DataAnnotations.dll
dotnet_nlp/rule_engine/dlls/System.ComponentModel.EventBasedAsync.dll
dotnet_nlp/rule_engine/dlls/System.ComponentModel.Primitives.dll
dotnet_nlp.rule_engine-1.3.2.dist-info/LICENSE
dotnet_nlp.rule_engine-1.3.2.dist-info/METADATA
dotnet_nlp.rule_engine-1.3.2.dist-info/WHEEL
dotnet_nlp.rule_engine-1.3.2.dist-info/top_level.txt
dotnet_nlp.rule_engine-1.3.2.dist-info/RECORD
